YoloOnnxDet/DirectML.dll
YoloOnnxDet/OnnxDet.dll
YoloOnnxDet/OnnxDet.py
YoloOnnxDet/OnnxDetMutTD.py
YoloOnnxDet/OnnxMutTD.dll
YoloOnnxDet/__init__.py
YoloOnnxDet/onnxruntime.dll
YoloOnnxDet/onnxruntime_providers_shared.dll
YoloOnnxDet/opencv_world480.dll
yoloonnxdet-0.1.3.dist-info/METADATA
yoloonnxdet-0.1.3.dist-info/WHEEL
yoloonnxdet-0.1.3.dist-info/top_level.txt
yoloonnxdet-0.1.3.dist-info/RECORD
