Metadata-Version: 2.4
Name: YoloOnnxDet
Version: 0.1.3
Summary: A Python package for yolo onnx model detect.
Home-page: https://github.com/zaixia108/PyYoloOnnxDetDll
Author: zaixia108
Author-email: zaixia108 <xvbowen2012@gmail.com>
Project-URL: homepage, https://github.com/zaixia108/PyYoloOnnxDetDll
Classifier: Programming Language :: Python :: 3
Classifier: License :: OSI Approved :: MIT License
Classifier: Operating System :: OS Independent
Requires-Python: >=3.8
Requires-Dist: opencv-python
Requires-Dist: numpy
Dynamic: author
Dynamic: home-page
Dynamic: requires-python
